<?xml version="1.0" encoding="UTF-8"?>
<mxfile host="Electron" modified="2020-01-08T23:04:40.874Z" agent="Mozilla/5.0 (Windows NT 10.0; Win64; x64) AppleWebKit/537.36 (KHTML, like Gecko) draw.io/12.4.2 Chrome/78.0.3904.130 Electron/7.1.4 Safari/537.36" etag="ncN9Psh96gId-EGCZ4u2" version="12.4.2" type="device" pages="1">
  <diagram id="DXtTnsnJ06EOFK5huowu" name="Page-1">
    <mxGraphModel dx="1086" dy="776" grid="1" gridSize="10" guides="1" tooltips="1" connect="1" arrows="1" fold="1" page="1" pageScale="1" pageWidth="850" pageHeight="1100" math="0" shadow="0">
      <root>
        <mxCell id="0"/>
        <mxCell id="1" parent="0"/>
        <mxCell id="dQbELXKlOdWI5xQTE6AN-2" value="&lt;p style=&quot;margin: 0px ; margin-top: 4px ; text-align: center&quot;&gt;&lt;br&gt;&lt;b&gt;Program&lt;/b&gt;&lt;/p&gt;" style="verticalAlign=top;align=left;overflow=fill;fontSize=12;fontFamily=Helvetica;html=1;" parent="1" vertex="1">
          <mxGeometry x="100" y="140" width="140" height="60" as="geometry"/>
        </mxCell>
        <mxCell id="dQbELXKlOdWI5xQTE6AN-3" value="&lt;p style=&quot;margin: 0px ; margin-top: 4px ; text-align: center&quot;&gt;&lt;br&gt;&lt;b&gt;ProgramHeader&lt;/b&gt;&lt;/p&gt;" style="verticalAlign=top;align=left;overflow=fill;fontSize=12;fontFamily=Helvetica;html=1;" parent="1" vertex="1">
          <mxGeometry x="350" y="140" width="140" height="60" as="geometry"/>
        </mxCell>
        <mxCell id="dQbELXKlOdWI5xQTE6AN-5" value="" style="align=right;html=1;verticalAlign=bottom;endArrow=none;startArrow=diamondThin;startSize=14;startFill=1;edgeStyle=none;exitX=0.5;exitY=1;exitDx=0;exitDy=0;entryX=0.014;entryY=0.65;entryDx=0;entryDy=0;entryPerimeter=0;" parent="1" source="dQbELXKlOdWI5xQTE6AN-2" target="dQbELXKlOdWI5xQTE6AN-15" edge="1">
          <mxGeometry x="1" relative="1" as="geometry">
            <mxPoint x="190" y="280" as="sourcePoint"/>
            <mxPoint x="350" y="280" as="targetPoint"/>
          </mxGeometry>
        </mxCell>
        <mxCell id="dQbELXKlOdWI5xQTE6AN-6" value="1" style="resizable=0;html=1;align=left;verticalAlign=top;labelBackgroundColor=none;fontSize=10" parent="dQbELXKlOdWI5xQTE6AN-5" connectable="0" vertex="1">
          <mxGeometry x="-1" relative="1" as="geometry"/>
        </mxCell>
        <mxCell id="dQbELXKlOdWI5xQTE6AN-7" value="1..*" style="resizable=0;html=1;align=right;verticalAlign=top;labelBackgroundColor=none;fontSize=10" parent="dQbELXKlOdWI5xQTE6AN-5" connectable="0" vertex="1">
          <mxGeometry x="1" relative="1" as="geometry"/>
        </mxCell>
        <mxCell id="dQbELXKlOdWI5xQTE6AN-8" value="" style="align=right;html=1;verticalAlign=bottom;endArrow=none;startArrow=diamondThin;startSize=14;startFill=1;edgeStyle=none;exitX=1;exitY=0.5;exitDx=0;exitDy=0;entryX=0;entryY=0.5;entryDx=0;entryDy=0;" parent="1" source="dQbELXKlOdWI5xQTE6AN-2" target="dQbELXKlOdWI5xQTE6AN-3" edge="1">
          <mxGeometry x="1" relative="1" as="geometry">
            <mxPoint x="250" y="170" as="sourcePoint"/>
            <mxPoint x="340" y="170" as="targetPoint"/>
          </mxGeometry>
        </mxCell>
        <mxCell id="dQbELXKlOdWI5xQTE6AN-9" value="1" style="resizable=0;html=1;align=left;verticalAlign=top;labelBackgroundColor=none;fontSize=10" parent="dQbELXKlOdWI5xQTE6AN-8" connectable="0" vertex="1">
          <mxGeometry x="-1" relative="1" as="geometry"/>
        </mxCell>
        <mxCell id="dQbELXKlOdWI5xQTE6AN-10" value="1" style="resizable=0;html=1;align=right;verticalAlign=top;labelBackgroundColor=none;fontSize=10" parent="dQbELXKlOdWI5xQTE6AN-8" connectable="0" vertex="1">
          <mxGeometry x="1" relative="1" as="geometry"/>
        </mxCell>
        <mxCell id="dQbELXKlOdWI5xQTE6AN-15" value="&lt;p style=&quot;margin: 0px ; margin-top: 4px ; text-align: center&quot;&gt;&lt;b&gt;PumpingJobSection&lt;/b&gt;&lt;/p&gt;&lt;hr size=&quot;1&quot;&gt;JobType&lt;div style=&quot;height: 2px&quot;&gt;&lt;/div&gt;&lt;hr size=&quot;1&quot;&gt;&lt;div style=&quot;height: 2px&quot;&gt;&lt;/div&gt;" style="verticalAlign=top;align=left;overflow=fill;fontSize=12;fontFamily=Helvetica;html=1;" parent="1" vertex="1">
          <mxGeometry x="350" y="260" width="140" height="80" as="geometry"/>
        </mxCell>
        <mxCell id="dQbELXKlOdWI5xQTE6AN-16" value="&lt;p style=&quot;margin: 0px ; margin-top: 4px ; text-align: center&quot;&gt;&lt;b&gt;CallSheet&lt;/b&gt;&lt;/p&gt;&lt;hr size=&quot;1&quot;&gt;JobType&lt;div style=&quot;height: 2px&quot;&gt;&lt;/div&gt;&lt;hr size=&quot;1&quot;&gt;&lt;div style=&quot;height: 2px&quot;&gt;RiskMatrix&lt;/div&gt;" style="verticalAlign=top;align=left;overflow=fill;fontSize=12;fontFamily=Helvetica;html=1;" parent="1" vertex="1">
          <mxGeometry x="65" y="390" width="140" height="90" as="geometry"/>
        </mxCell>
        <mxCell id="dQbELXKlOdWI5xQTE6AN-20" value="&amp;lt;&amp;lt;stereotype&amp;gt;&amp;gt;&#xa;dependency1" style="edgeStyle=none;html=1;endArrow=open;endSize=12;dashed=1;verticalAlign=bottom;entryX=0.5;entryY=1;entryDx=0;entryDy=0;exitX=1;exitY=0.5;exitDx=0;exitDy=0;" parent="1" source="dQbELXKlOdWI5xQTE6AN-16" target="dQbELXKlOdWI5xQTE6AN-15" edge="1">
          <mxGeometry width="160" relative="1" as="geometry">
            <mxPoint x="70" y="470" as="sourcePoint"/>
            <mxPoint x="230" y="470" as="targetPoint"/>
          </mxGeometry>
        </mxCell>
        <mxCell id="dQbELXKlOdWI5xQTE6AN-21" value="" style="verticalAlign=bottom;html=1;endArrow=open;endSize=12;edgeStyle=orthogonalEdgeStyle;entryX=0.25;entryY=1;entryDx=0;entryDy=0;exitX=0.5;exitY=0;exitDx=0;exitDy=0;" parent="1" source="dQbELXKlOdWI5xQTE6AN-16" target="dQbELXKlOdWI5xQTE6AN-2" edge="1">
          <mxGeometry x="0.0526" y="15" relative="1" as="geometry">
            <mxPoint x="135" y="380" as="sourcePoint"/>
            <mxPoint x="320" y="470" as="targetPoint"/>
            <mxPoint as="offset"/>
          </mxGeometry>
        </mxCell>
        <mxCell id="dQbELXKlOdWI5xQTE6AN-22" value="0..*" style="resizable=0;html=1;align=left;verticalAlign=top;labelBackgroundColor=none;fontSize=10" parent="dQbELXKlOdWI5xQTE6AN-21" connectable="0" vertex="1">
          <mxGeometry x="-1" relative="1" as="geometry">
            <mxPoint x="5" y="-40" as="offset"/>
          </mxGeometry>
        </mxCell>
        <mxCell id="dQbELXKlOdWI5xQTE6AN-23" value="1" style="resizable=0;html=1;align=right;verticalAlign=top;labelBackgroundColor=none;fontSize=10" parent="dQbELXKlOdWI5xQTE6AN-21" connectable="0" vertex="1">
          <mxGeometry x="0.9" relative="1" as="geometry">
            <mxPoint x="15" y="11" as="offset"/>
          </mxGeometry>
        </mxCell>
        <mxCell id="dQbELXKlOdWI5xQTE6AN-24" value="" style="resizable=0;html=1;align=right;verticalAlign=bottom;labelBackgroundColor=none;fontSize=10" parent="dQbELXKlOdWI5xQTE6AN-21" connectable="0" vertex="1">
          <mxGeometry x="0.9" relative="1" as="geometry"/>
        </mxCell>
        <mxCell id="dQbELXKlOdWI5xQTE6AN-26" value="&lt;p style=&quot;margin: 0px ; margin-top: 4px ; text-align: center&quot;&gt;&lt;b&gt;RigJob&lt;/b&gt;&lt;/p&gt;&lt;hr size=&quot;1&quot;&gt;JobType&lt;div style=&quot;height: 2px&quot;&gt;&lt;/div&gt;&lt;hr size=&quot;1&quot;&gt;&lt;div style=&quot;height: 2px&quot;&gt;RiskMatrix&lt;/div&gt;" style="verticalAlign=top;align=left;overflow=fill;fontSize=12;fontFamily=Helvetica;html=1;" parent="1" vertex="1">
          <mxGeometry x="65" y="600" width="140" height="80" as="geometry"/>
        </mxCell>
        <mxCell id="dQbELXKlOdWI5xQTE6AN-27" value="" style="verticalAlign=bottom;html=1;endArrow=open;endSize=12;edgeStyle=orthogonalEdgeStyle;entryX=0.25;entryY=1;entryDx=0;entryDy=0;" parent="1" source="dQbELXKlOdWI5xQTE6AN-26" edge="1">
          <mxGeometry x="0.0526" y="15" relative="1" as="geometry">
            <mxPoint x="134.5" y="670" as="sourcePoint"/>
            <mxPoint x="134.5" y="480" as="targetPoint"/>
            <mxPoint as="offset"/>
          </mxGeometry>
        </mxCell>
        <mxCell id="dQbELXKlOdWI5xQTE6AN-28" value="1" style="resizable=0;html=1;align=left;verticalAlign=top;labelBackgroundColor=none;fontSize=10" parent="dQbELXKlOdWI5xQTE6AN-27" connectable="0" vertex="1">
          <mxGeometry x="-1" relative="1" as="geometry">
            <mxPoint x="5" y="-40" as="offset"/>
          </mxGeometry>
        </mxCell>
        <mxCell id="dQbELXKlOdWI5xQTE6AN-29" value="1" style="resizable=0;html=1;align=right;verticalAlign=top;labelBackgroundColor=none;fontSize=10" parent="dQbELXKlOdWI5xQTE6AN-27" connectable="0" vertex="1">
          <mxGeometry x="0.9" relative="1" as="geometry">
            <mxPoint x="15" y="11" as="offset"/>
          </mxGeometry>
        </mxCell>
        <mxCell id="dQbELXKlOdWI5xQTE6AN-30" value="" style="resizable=0;html=1;align=right;verticalAlign=bottom;labelBackgroundColor=none;fontSize=10" parent="dQbELXKlOdWI5xQTE6AN-27" connectable="0" vertex="1">
          <mxGeometry x="0.9" relative="1" as="geometry"/>
        </mxCell>
      </root>
    </mxGraphModel>
  </diagram>
</mxfile>
